ms_recognizers_sequence/__init__.py
ms_recognizers_sequence/resources/__init__.py
ms_recognizers_sequence/resources/base_GUID.py
ms_recognizers_sequence/resources/base_email.py
ms_recognizers_sequence/resources/base_hashtag.py
ms_recognizers_sequence/resources/base_ip.py
ms_recognizers_sequence/resources/base_mention.py
ms_recognizers_sequence/resources/base_phone_numbers.py
ms_recognizers_sequence/resources/base_url.py
ms_recognizers_sequence/resources/chinese_ip.py
ms_recognizers_sequence/resources/chinese_phone_numbers.py
ms_recognizers_sequence/resources/chinese_url.py
ms_recognizers_sequence/resources/english_phone_numbers.py
ms_recognizers_sequence/resources/portuguese_phone_numbers.py
ms_recognizers_sequence/sequence/__init__.py
ms_recognizers_sequence/sequence/constants.py
ms_recognizers_sequence/sequence/extractors.py
ms_recognizers_sequence/sequence/models.py
ms_recognizers_sequence/sequence/parsers.py
ms_recognizers_sequence/sequence/sequence_recognizer.py
ms_recognizers_sequence/sequence/chinese/__init__.py
ms_recognizers_sequence/sequence/chinese/extractors.py
ms_recognizers_sequence/sequence/config/__init__.py
ms_recognizers_sequence/sequence/config/base_phone_number_configuration.py
ms_recognizers_sequence/sequence/config/ip_configuration.py
ms_recognizers_sequence/sequence/config/phone_number_configuration.py
ms_recognizers_sequence/sequence/config/url_configuration.py
ms_recognizers_sequence/sequence/english/__init__.py
ms_recognizers_sequence/sequence/english/extractors.py
ms_recognizers_sequence/sequence/english/parsers.py
ms_recognizers_sequence/sequence/portuguese/__init__.py
ms_recognizers_sequence/sequence/portuguese/extractors.py
recognizers_sequence/__init__.py
recognizers_sequence/resources/__init__.py
recognizers_sequence/resources/base_GUID.py
recognizers_sequence/resources/base_email.py
recognizers_sequence/resources/base_hashtag.py
recognizers_sequence/resources/base_ip.py
recognizers_sequence/resources/base_mention.py
ms_recognizers_text_sequence-1.0.1.dist-info/METADATA
ms_recognizers_text_sequence-1.0.1.dist-info/WHEEL
ms_recognizers_text_sequence-1.0.1.dist-info/top_level.txt
ms_recognizers_text_sequence-1.0.1.dist-info/RECORD
