Metadata-Version: 2.1
Name: ms-recognizers-text-sequence
Version: 1.0.1
Summary: recognizers-text-sequence README
Home-page: https://github.com/Microsoft/Recognizers-Text
Author: Microsoft
License: MIT
Keywords: nlp,nlp-entity-extraction,entity-extraction,parser-library
Classifier: Programming Language :: Python :: 3.6
Classifier: Intended Audience :: Developers
Classifier: License :: OSI Approved :: MIT License
Classifier: Operating System :: OS Independent
Classifier: Development Status :: 3 - Alpha
Classifier: Topic :: Scientific/Engineering :: Artificial Intelligence
Requires-Dist: ms-recognizers-text
Requires-Dist: ms-recognizers-text-number
Requires-Dist: regex
